tehom/__init__.py
tehom/__main__.py
tehom/_persistence.py
tehom/_version.py
tehom/downloads.py
tehom/tests/conftest.py
tehom/tests/test_downloads.py
tehom/tests/test_persistence.py
tehom-0.0.1.dist-info/LICENSE
tehom-0.0.1.dist-info/METADATA
tehom-0.0.1.dist-info/WHEEL
tehom-0.0.1.dist-info/entry_points.txt
tehom-0.0.1.dist-info/top_level.txt
tehom-0.0.1.dist-info/RECORD
