Metadata-Version: 2.1
Name: tehom
Version: 0.0.1
Summary: Transform underwater acoustic data into training data for machine learning.
Author-email: Jake Stevens-Haas <jacob.stevens.haas@gmail.com>
License: AGPL
Project-URL: Bug Tracker, https://github.com/Jacob-Stevens-Haas/tehom/issues
Project-URL: Documentation, https://tehom.readthedocs.io/en/latest/
Project-URL: Source Code, https://github.com/Jacob-Stevens-Haas/tehom
Platform: any
Classifier: Development Status :: 2 - Pre-Alpha
Classifier: Environment :: Console
Classifier: Intended Audience :: Science/Research
Classifier: License :: OSI Approved :: GNU Affero General Public License v3
Classifier: Operating System :: OS Independent
Classifier: Programming Language :: Python :: 3.7
Classifier: Programming Language :: Python :: 3.8
Classifier: Programming Language :: Python :: 3.9
Classifier: Programming Language :: Python :: 3.10
Classifier: Topic :: Scientific/Engineering
Classifier: Topic :: Multimedia :: Sound/Audio
Classifier: Topic :: Scientific/Engineering :: Artificial Intelligence
Classifier: Topic :: Scientific/Engineering :: Mathematics
Requires-Python: >=3.7
License-File: LICENSE
Requires-Dist: pandas
Requires-Dist: matplotlib
Requires-Dist: numpy
Requires-Dist: plotly
Requires-Dist: onc (==2.3.5)
Requires-Dist: sqlalchemy
Requires-Dist: spans
Requires-Dist: requests
Requires-Dist: nbformat (~=5.7)
Provides-Extra: dev
Requires-Dist: coverage ; extra == 'dev'
Requires-Dist: black ; extra == 'dev'
Requires-Dist: flake8 ; extra == 'dev'
Requires-Dist: flake8-comprehensions ; extra == 'dev'
Requires-Dist: isort ; extra == 'dev'
Requires-Dist: pre-commit ; extra == 'dev'
Requires-Dist: pip ; extra == 'dev'
Requires-Dist: pytest ; extra == 'dev'
Requires-Dist: twine ; extra == 'dev'
Requires-Dist: wheel ; extra == 'dev'
Requires-Dist: build (~=0.9) ; extra == 'dev'
Provides-Extra: docs
Requires-Dist: sphinx (==6.0.0) ; extra == 'docs'
Requires-Dist: sphinxcontrib-apidoc ; extra == 'docs'
